noideacore/README.md
noideacore/__init__.py
noideacore/basic_features.py
noideacore/com.py
noideacore/controller.py
noideacore/data/__init__.py
noideacore/data/__pycache__/__init__.cpython-311.pyc
noideacore/data/__pycache__/data.cpython-311.pyc
noideacore/data/__pycache__/graph.cpython-311.pyc
noideacore/data/data.py
noideacore/data/graph.py
noideacore/data/html/__init__.py
noideacore/data/html/__pycache__/__init__.cpython-311.pyc
noideacore/data/html/__pycache__/charts.cpython-311.pyc
noideacore/data/html/charts.py
noideacore/dates.py
noideacore/encrypt.py
noideacore/sql.py
noideacore/terminal/__init__.py
noideacore/terminal/__pycache__/__init__.cpython-311.pyc
noideacore/terminal/__pycache__/example_usage.cpython-311.pyc
noideacore/terminal/__pycache__/terminal_exe.cpython-311.pyc
noideacore/terminal/example_usage.py
noideacore/terminal/terminal_exe.py
noideacore-1.4.1.dist-info/LICENSE
noideacore-1.4.1.dist-info/METADATA
noideacore-1.4.1.dist-info/WHEEL
noideacore-1.4.1.dist-info/RECORD
