Metadata-Version: 2.3
Name: noideacore
Version: 1.4.1
Summary: 
Author: No1d3a
Requires-Python: >=3.11,<4.0
Classifier: Programming Language :: Python :: 3
Classifier: Programming Language :: Python :: 3.11
Classifier: Programming Language :: Python :: 3.12
Classifier: Programming Language :: Python :: 3.13
Requires-Dist: mysql-connector-python (>=8.4.0,<9.0.0)
Requires-Dist: mysql-connector-repackaged (>=0.3.1,<0.4.0)
Requires-Dist: pycryptodomex (==3.20.0)
Requires-Dist: python_dateutil (==2.8.2)
